cppvec/LICENSE
cppvec/README.MD
cppvec/__init__.py
cppvec/batchcompile.py
cppvec/cppvect.pyx
cppvec/cppvect_compile.py
cppvec/requirements.txt
cppvec/thirdparty.json
cppvec-0.10.dist-info/LICENSE.rst
cppvec-0.10.dist-info/METADATA
cppvec-0.10.dist-info/WHEEL
cppvec-0.10.dist-info/top_level.txt
cppvec-0.10.dist-info/RECORD
