Metadata-Version: 2.1
Name: cppvec
Version: 0.10
Summary: C++ vectors with Python indexing
Home-page: https://github.com/hansalemaos/cppvec
Author: Johannes Fischer
Author-email: aulasparticularesdealemaosp@gmail.com
License: MIT
Keywords: c++,vector
Classifier: Development Status :: 4 - Beta
Classifier: Programming Language :: Python :: 3 :: Only
Classifier: Programming Language :: Python :: 3.10
Classifier: Topic :: Software Development :: Libraries :: Python Modules
Classifier: Topic :: Utilities
License-File: LICENSE.rst
Requires-Dist: Cython
Requires-Dist: numpy
Requires-Dist: setuptools
